{
  "objects": [
    {
      "label": "3d_human_skeleton",
      "keypoints": [
        {
          "id": "2",
          "position": {
            "x": -0.11748321,
            "y": 0.533679,
            "z": 1.6673951
          }
        },
        {
          "id": "17",
          "position": {
            "x": -0.16964763,
            "y": 0.56445944,
            "z": 1.7013988
          }
        },
        {
          "id": "16",
          "position": {
            "x": -0.093708076,
            "y": 0.485902,
            "z": 1.6910987
          }
        },
        {
          "id": "19",
          "position": {
            "x": -0.23441094,
            "y": 0.551978,
            "z": 1.6846138
          }
        },
        {
          "id": "18",
          "position": {
            "x": -0.13974123,
            "y": 0.41346067,
            "z": 1.6706581
          }
        },
        {
          "id": "7",
          "position": {
            "x": -0.34406295,
            "y": 0.56540304,
            "z": 1.5010914
          }
        },
        {
          "id": "4",
          "position": {
            "x": -0.102529444,
            "y": 0.37667745,
            "z": 1.4701518
          }
        },
        {
          "id": "8",
          "position": {
            "x": -0.23607214,
            "y": 0.7500468,
            "z": 1.4342943
          }
        },
        {
          "id": "5",
          "position": {
            "x": 0.008912175,
            "y": 0.40893662,
            "z": 1.2554418
          }
        },
        {
          "id": "9",
          "position": {
            "x": -0.012549427,
            "y": 0.9130773,
            "z": 1.5572358
          }
        },
        {
          "id": "6",
          "position": {
            "x": 0.0152074965,
            "y": 0.35775548,
            "z": 0.93825823
          }
        },
        {
          "id": "13",
          "position": {
            "x": -0.27815259,
            "y": 0.54992986,
            "z": 0.9267843
          }
        },
        {
          "id": "10",
          "position": {
            "x": -0.113974355,
            "y": 0.4614911,
            "z": 0.9212013
          }
        },
        {
          "id": "14",
          "position": {
            "x": -0.2966819,
            "y": 0.48547658,
            "z": 0.50661653
          }
        },
        {
          "id": "11",
          "position": {
            "x": -0.12363666,
            "y": 0.441616,
            "z": 0.5108976
          }
        },
        {
          "id": "15",
          "position": {
            "x": -0.32122126,
            "y": 0.4493884,
            "z": 0.09919824
          }
        },
        {
          "id": "12",
          "position": {
            "x": -0.14369218,
            "y": 0.40800083,
            "z": 0.11558543
          }
        }
      ]
    },
    {
      "label": "3d_human_skeleton",
      "id": "1",
      "keypoints": [
        {
          "id": "2",
          "position": {
            "x": 2.2376277,
            "y": -0.65821844,
            "z": 1.0604494
          }
        },
        {
          "id": "17",
          "position": {
            "x": 2.2298186,
            "y": -0.62309754,
            "z": 1.0883386
          }
        },
        {
          "id": "16",
          "position": {
            "x": 2.2128117,
            "y": -0.68398833,
            "z": 1.0939488
          }
        },
        {
          "id": "19",
          "position": {
            "x": 2.2021978,
            "y": -0.5653381,
            "z": 1.1035804
          }
        },
        {
          "id": "18",
          "position": {
            "x": 2.0875452,
            "y": -0.6894547,
            "z": 1.0810723
          }
        },
        {
          "id": "7",
          "position": {
            "x": 2.2369545,
            "y": -0.4891665,
            "z": 0.9597341
          }
        },
        {
          "id": "4",
          "position": {
            "x": 1.9678715,
            "y": -0.73878074,
            "z": 0.9207014
          }
        },
        {
          "id": "8",
          "position": {
            "x": 2.2658646,
            "y": -0.43426457,
            "z": 0.67841905
          }
        },
        {
          "id": "5",
          "position": {
            "x": 1.870897,
            "y": -0.81135184,
            "z": 0.64285535
          }
        },
        {
          "id": "9",
          "position": {
            "x": 2.165388,
            "y": -0.61024725,
            "z": 0.62065226
          }
        },
        {
          "id": "6",
          "position": {
            "x": 2.0874372,
            "y": -0.70017743,
            "z": 0.62681663
          }
        },
        {
          "id": "13",
          "position": {
            "x": 2.0950012,
            "y": -0.45058948,
            "z": 0.4352167
          }
        },
        {
          "id": "10",
          "position": {
            "x": 1.8946301,
            "y": -0.61772573,
            "z": 0.3661967
          }
        },
        {
          "id": "14",
          "position": {
            "x": 2.3145726,
            "y": -0.5098202,
            "z": 0.61454004
          }
        },
        {
          "id": "11",
          "position": {
            "x": 1.9499968,
            "y": -0.7818653,
            "z": 0.42294046
          }
        },
        {
          "id": "15",
          "position": {
            "x": 2.2147465,
            "y": -0.23730154,
            "z": 0.3478294
          }
        },
        {
          "id": "12",
          "position": {
            "x": 1.83461,
            "y": -0.6032709,
            "z": 0.12764208
          }
        }
      ]
    }
  ]
}