{
  "objects": [
    {
      "label": "3d_human_skeleton",
      "keypoints": [
        {
          "id": "2",
          "position": {
            "x": -0.13842045,
            "y": 0.5424964,
            "z": 1.6735337
          }
        },
        {
          "id": "17",
          "position": {
            "x": -0.17602426,
            "y": 0.5642085,
            "z": 1.7033958
          }
        },
        {
          "id": "16",
          "position": {
            "x": -0.10926692,
            "y": 0.4873991,
            "z": 1.6964971
          }
        },
        {
          "id": "19",
          "position": {
            "x": -0.23746404,
            "y": 0.5592828,
            "z": 1.6849099
          }
        },
        {
          "id": "18",
          "position": {
            "x": -0.14067397,
            "y": 0.42127994,
            "z": 1.674445
          }
        },
        {
          "id": "7",
          "position": {
            "x": -0.33706918,
            "y": 0.5589116,
            "z": 1.4676701
          }
        },
        {
          "id": "4",
          "position": {
            "x": -0.12684986,
            "y": 0.327022,
            "z": 1.4649454
          }
        },
        {
          "id": "8",
          "position": {
            "x": -0.36105484,
            "y": 0.6404835,
            "z": 1.1772946
          }
        },
        {
          "id": "5",
          "position": {
            "x": -0.066463195,
            "y": 0.3356252,
            "z": 1.168792
          }
        },
        {
          "id": "9",
          "position": {
            "x": -0.36186764,
            "y": 0.75806,
            "z": 0.958926
          }
        },
        {
          "id": "6",
          "position": {
            "x": -0.0059018447,
            "y": 0.34852034,
            "z": 0.91083777
          }
        },
        {
          "id": "13",
          "position": {
            "x": -0.28659448,
            "y": 0.53231055,
            "z": 0.91903627
          }
        },
        {
          "id": "10",
          "position": {
            "x": -0.13383621,
            "y": 0.42782018,
            "z": 0.9136987
          }
        },
        {
          "id": "14",
          "position": {
            "x": -0.303375,
            "y": 0.4947964,
            "z": 0.4988379
          }
        },
        {
          "id": "11",
          "position": {
            "x": -0.12732251,
            "y": 0.44702935,
            "z": 0.5176198
          }
        },
        {
          "id": "15",
          "position": {
            "x": -0.32749945,
            "y": 0.44429335,
            "z": 0.09567828
          }
        },
        {
          "id": "12",
          "position": {
            "x": -0.14353532,
            "y": 0.407121,
            "z": 0.124448866
          }
        }
      ]
    },
    {
      "label": "3d_human_skeleton",
      "id": "1",
      "keypoints": [
        {
          "id": "2",
          "position": {
            "x": 2.291249,
            "y": -0.6713457,
            "z": 1.0875955
          }
        },
        {
          "id": "17",
          "position": {
            "x": 2.2911737,
            "y": -0.61331207,
            "z": 1.1126268
          }
        },
        {
          "id": "16",
          "position": {
            "x": 2.2540648,
            "y": -0.727206,
            "z": 1.1178443
          }
        },
        {
          "id": "19",
          "position": {
            "x": 2.2540643,
            "y": -0.5610184,
            "z": 1.1202792
          }
        },
        {
          "id": "18",
          "position": {
            "x": 2.1519518,
            "y": -0.69251883,
            "z": 1.107669
          }
        },
        {
          "id": "7",
          "position": {
            "x": 2.2948315,
            "y": -0.46355453,
            "z": 0.9690673
          }
        },
        {
          "id": "4",
          "position": {
            "x": 2.026616,
            "y": -0.72450703,
            "z": 0.95283705
          }
        },
        {
          "id": "8",
          "position": {
            "x": 2.3357823,
            "y": -0.40226534,
            "z": 0.7120999
          }
        },
        {
          "id": "5",
          "position": {
            "x": 1.9232728,
            "y": -0.7947187,
            "z": 0.70056385
          }
        },
        {
          "id": "9",
          "position": {
            "x": 2.2316236,
            "y": -0.5589797,
            "z": 0.6645193
          }
        },
        {
          "id": "6",
          "position": {
            "x": 2.0958557,
            "y": -0.7263824,
            "z": 0.6362736
          }
        },
        {
          "id": "13",
          "position": {
            "x": 2.1543522,
            "y": -0.4321001,
            "z": 0.4758815
          }
        },
        {
          "id": "10",
          "position": {
            "x": 1.9691842,
            "y": -0.60857135,
            "z": 0.43379837
          }
        },
        {
          "id": "14",
          "position": {
            "x": 2.3209732,
            "y": -0.44344357,
            "z": 0.5707023
          }
        },
        {
          "id": "11",
          "position": {
            "x": 1.9776714,
            "y": -0.7747474,
            "z": 0.49682105
          }
        },
        {
          "id": "15",
          "position": {
            "x": 2.06674,
            "y": -0.41536188,
            "z": 0.18267527
          }
        },
        {
          "id": "12",
          "position": {
            "x": 1.8685371,
            "y": -0.6423239,
            "z": 0.15018027
          }
        }
      ]
    }
  ]
}