{
  "objects": [
    {
      "label": "3d_human_skeleton",
      "keypoints": [
        {
          "id": "2",
          "position": {
            "x": -0.0882785,
            "y": 0.54062843,
            "z": 1.683485
          }
        },
        {
          "id": "17",
          "position": {
            "x": -0.16556674,
            "y": 0.6009877,
            "z": 1.7220324
          }
        },
        {
          "id": "16",
          "position": {
            "x": -0.09213263,
            "y": 0.5244695,
            "z": 1.7125478
          }
        },
        {
          "id": "19",
          "position": {
            "x": -0.24205896,
            "y": 0.56753635,
            "z": 1.6832056
          }
        },
        {
          "id": "18",
          "position": {
            "x": -0.13025638,
            "y": 0.47403458,
            "z": 1.6846069
          }
        },
        {
          "id": "7",
          "position": {
            "x": -0.35162124,
            "y": 0.5539976,
            "z": 1.4641844
          }
        },
        {
          "id": "4",
          "position": {
            "x": -0.0919147,
            "y": 0.42154703,
            "z": 1.5350413
          }
        },
        {
          "id": "8",
          "position": {
            "x": -0.3906556,
            "y": 0.52058065,
            "z": 1.1671027
          }
        },
        {
          "id": "5",
          "position": {
            "x": 0.046337783,
            "y": 0.35146815,
            "z": 1.7387034
          }
        },
        {
          "id": "9",
          "position": {
            "x": -0.4092809,
            "y": 0.5488751,
            "z": 0.91594857
          }
        },
        {
          "id": "6",
          "position": {
            "x": 0.16164236,
            "y": 0.287877,
            "z": 1.9533713
          }
        },
        {
          "id": "13",
          "position": {
            "x": -0.25401494,
            "y": 0.54872227,
            "z": 0.941343
          }
        },
        {
          "id": "10",
          "position": {
            "x": -0.089770354,
            "y": 0.48553774,
            "z": 0.94925004
          }
        },
        {
          "id": "14",
          "position": {
            "x": -0.2899972,
            "y": 0.5100967,
            "z": 0.5196533
          }
        },
        {
          "id": "11",
          "position": {
            "x": -0.115211055,
            "y": 0.45089805,
            "z": 0.52309203
          }
        },
        {
          "id": "15",
          "position": {
            "x": -0.3250019,
            "y": 0.45267802,
            "z": 0.10623729
          }
        },
        {
          "id": "12",
          "position": {
            "x": -0.14471717,
            "y": 0.4038792,
            "z": 0.13023841
          }
        }
      ]
    },
    {
      "label": "3d_human_skeleton",
      "id": "1",
      "keypoints": [
        {
          "id": "2",
          "position": {
            "x": 2.405022,
            "y": -0.7573854,
            "z": 1.0075465
          }
        },
        {
          "id": "17",
          "position": {
            "x": 2.4074962,
            "y": -0.7278465,
            "z": 1.0421506
          }
        },
        {
          "id": "16",
          "position": {
            "x": 2.37082,
            "y": -0.77799994,
            "z": 1.0363902
          }
        },
        {
          "id": "19",
          "position": {
            "x": 2.3684611,
            "y": -0.658738,
            "z": 1.0679148
          }
        },
        {
          "id": "18",
          "position": {
            "x": 2.254224,
            "y": -0.778535,
            "z": 1.0307574
          }
        },
        {
          "id": "7",
          "position": {
            "x": 2.3879478,
            "y": -0.57322603,
            "z": 0.8928401
          }
        },
        {
          "id": "4",
          "position": {
            "x": 2.1522338,
            "y": -0.84735656,
            "z": 0.9012329
          }
        },
        {
          "id": "8",
          "position": {
            "x": 2.3699965,
            "y": -0.5013545,
            "z": 0.64917517
          }
        },
        {
          "id": "5",
          "position": {
            "x": 2.0840337,
            "y": -0.86350554,
            "z": 0.6387176
          }
        },
        {
          "id": "9",
          "position": {
            "x": 2.2333255,
            "y": -0.7349847,
            "z": 0.6637462
          }
        },
        {
          "id": "6",
          "position": {
            "x": 2.2314763,
            "y": -0.7558845,
            "z": 0.7115179
          }
        },
        {
          "id": "13",
          "position": {
            "x": 1.8987305,
            "y": -0.21644305,
            "z": 0.64785826
          }
        },
        {
          "id": "10",
          "position": {
            "x": 1.7309747,
            "y": -0.36453694,
            "z": 0.6072986
          }
        },
        {
          "id": "14",
          "position": {
            "x": 2.1979558,
            "y": -0.49032456,
            "z": 0.6214608
          }
        },
        {
          "id": "11",
          "position": {
            "x": 1.9169468,
            "y": -0.6299745,
            "z": 0.6949929
          }
        },
        {
          "id": "15",
          "position": {
            "x": 1.9098126,
            "y": -0.36382654,
            "z": 0.5856381
          }
        },
        {
          "id": "12",
          "position": {
            "x": 1.6848545,
            "y": -0.26409492,
            "z": 0.39434338
          }
        }
      ]
    }
  ]
}