{
  "objects": [
    {
      "label": "3d_human_skeleton",
      "keypoints": [
        {
          "id": "2",
          "position": {
            "x": -0.13203141,
            "y": 0.66849434,
            "z": 1.667063
          }
        },
        {
          "id": "17",
          "position": {
            "x": -0.15208505,
            "y": 0.6852521,
            "z": 1.697026
          }
        },
        {
          "id": "16",
          "position": {
            "x": -0.14769287,
            "y": 0.6528814,
            "z": 1.6928369
          }
        },
        {
          "id": "19",
          "position": {
            "x": -0.25665173,
            "y": 0.7420301,
            "z": 1.677092
          }
        },
        {
          "id": "18",
          "position": {
            "x": -0.2285275,
            "y": 0.5624539,
            "z": 1.6667535
          }
        },
        {
          "id": "7",
          "position": {
            "x": -0.30797714,
            "y": 0.8136284,
            "z": 1.4581673
          }
        },
        {
          "id": "4",
          "position": {
            "x": -0.25249597,
            "y": 0.48008323,
            "z": 1.4692494
          }
        },
        {
          "id": "8",
          "position": {
            "x": -0.3096456,
            "y": 0.8629774,
            "z": 1.1610926
          }
        },
        {
          "id": "5",
          "position": {
            "x": -0.10343315,
            "y": 0.32615003,
            "z": 1.2725986
          }
        },
        {
          "id": "9",
          "position": {
            "x": -0.22543079,
            "y": 0.89854074,
            "z": 0.92021114
          }
        },
        {
          "id": "6",
          "position": {
            "x": 0.16135043,
            "y": 0.24552853,
            "z": 1.2387053
          }
        },
        {
          "id": "13",
          "position": {
            "x": -0.26082522,
            "y": 0.74099153,
            "z": 0.9232101
          }
        },
        {
          "id": "10",
          "position": {
            "x": -0.23371471,
            "y": 0.53049177,
            "z": 0.9141381
          }
        },
        {
          "id": "14",
          "position": {
            "x": -0.26214114,
            "y": 0.72559476,
            "z": 0.5182363
          }
        },
        {
          "id": "11",
          "position": {
            "x": -0.25655803,
            "y": 0.51345634,
            "z": 0.51934063
          }
        },
        {
          "id": "15",
          "position": {
            "x": -0.30053574,
            "y": 0.7417301,
            "z": 0.10874314
          }
        },
        {
          "id": "12",
          "position": {
            "x": -0.29106653,
            "y": 0.4854068,
            "z": 0.12209662
          }
        }
      ]
    },
    {
      "label": "3d_human_skeleton",
      "id": "1",
      "keypoints": [
        {
          "id": "2",
          "position": {
            "x": 1.9745685,
            "y": -0.30834725,
            "z": 1.1125004
          }
        },
        {
          "id": "17",
          "position": {
            "x": 2.0027761,
            "y": -0.28297746,
            "z": 1.1428243
          }
        },
        {
          "id": "16",
          "position": {
            "x": 1.912597,
            "y": -0.31515366,
            "z": 1.1483685
          }
        },
        {
          "id": "19",
          "position": {
            "x": 1.9675212,
            "y": -0.15229817,
            "z": 1.13534
          }
        },
        {
          "id": "18",
          "position": {
            "x": 1.8434381,
            "y": -0.2620058,
            "z": 1.1684076
          }
        },
        {
          "id": "7",
          "position": {
            "x": 1.9687333,
            "y": -0.06226539,
            "z": 0.9611841
          }
        },
        {
          "id": "4",
          "position": {
            "x": 1.7232974,
            "y": -0.2844766,
            "z": 1.0426006
          }
        },
        {
          "id": "8",
          "position": {
            "x": 2.161796,
            "y": -0.2146066,
            "z": 0.82449335
          }
        },
        {
          "id": "5",
          "position": {
            "x": 1.6677076,
            "y": -0.59031606,
            "z": 1.0453775
          }
        },
        {
          "id": "9",
          "position": {
            "x": 2.1195989,
            "y": -0.385451,
            "z": 1.0046196
          }
        },
        {
          "id": "6",
          "position": {
            "x": 1.9082583,
            "y": -0.5224556,
            "z": 1.1140764
          }
        },
        {
          "id": "13",
          "position": {
            "x": 1.9818815,
            "y": -0.23066173,
            "z": 0.5087635
          }
        },
        {
          "id": "10",
          "position": {
            "x": 1.7984618,
            "y": -0.38378108,
            "z": 0.48526362
          }
        },
        {
          "id": "14",
          "position": {
            "x": 2.2716272,
            "y": -0.5025206,
            "z": 0.47183424
          }
        },
        {
          "id": "11",
          "position": {
            "x": 2.0381565,
            "y": -0.70213157,
            "z": 0.4419114
          }
        },
        {
          "id": "15",
          "position": {
            "x": 2.016909,
            "y": -0.32761693,
            "z": 0.22030137
          }
        },
        {
          "id": "12",
          "position": {
            "x": 1.8980936,
            "y": -0.6314074,
            "z": 0.18152593
          }
        }
      ]
    }
  ]
}